Workbook

Sheet README
B1: Working Capital & Cash Flow Deep-Dive
B2: A head-to-head of two energy-equipment companies on how efficiently each converts operations into cash.
B4: IMPORTANT — ILLUSTRATIVE DATA
B5: Alpha Systems' and 'Beta Energy' are fictional companies with synthetic but realistic figures, built to demonstrate the analysis method on a clean dataset. The numbers are not drawn from any real company's accounts.
B7: WHAT THIS MODEL DOES
B8: Measures how much cash each company ties up in its operating cycle, using the cash conversion cycle (CCC) and net working capital (NWC) as a % of revenue, then quantifies two that would release cash at the weaker performer, with trade-offs.
B10: HOW TO USE IT
B11: 1. 'Inputs' holds every raw figure (blue = input).
B12: 2. 'WC Analysis' calculates DSO, DIO, DPO, CCC and NWC% with live formulas linked to 'Inputs'. Change an input, everything updates.
B13: 3. 'Levers' turns the gap to the leaner peer into an estimated $ of cash that could be released.
B15: FORMULAS
B16: DSO = Receivables / Revenue x 365
B17: DIO = Inventory / COGS x 365
B18: DPO = Payables / COGS x 365 | C18: COGS used as approximation for purchases
B19: CCC = DSO + DIO - DPO
B20: NWC% = (Receivables + Inventory - Payables) / Revenue.
B23: All figures in US$ millions. Illustrative model prepared July 2026.

Sheet Inputs
B1: INPUTS — raw financials (US$mm, illustrative)
B2: Blue = hardcoded input. Synthetic data for two fictional companies.
B4: ALPHA SUBSEA SYSTEMS
B5: Line item / US$mm | D5: FY2022 | E5: FY2023 | F5: FY2024
B6: Revenue | D6: 3200 | E6: 3650 | F6: 4050
B7: Cost of revenue (COGS) | D7: 2500 | E7: 2850 | F7: 3160
B8: Receivables, net | D8: 720 | E8: 880 | F8: 1010
B9: Inventories, net | D9: 780 | E9: 900 | F9: 1010
B10: Accounts payable | D10: 420 | E10: 470 | F10: 520
B12: BETA ENERGY EQUIPMENT
B13: Line item / US$mm | D13: FY2022 | E13: FY2023 | F13: FY2024
B14: Revenue | D14: 5400 | E14: 6100 | F14: 6700
B15: Cost of revenue (COGS) | D15: 4320 | E15: 4880 | F15: 5360
B16: Receivables, net | D16: 760 | E16: 850 | F16: 930
B17: Inventories, net | D17: 720 | E17: 800 | F17: 870
B18: Accounts payable | D18: 900 | E18: 1020 | F18: 1120

Sheet WC Analysis
B1: WORKING CAPITAL ANALYSIS — Cash Conversion Cycle
B2: All cells are live formulas linked to 'Inputs'. Ratios use period-end balances. Days basis = 365.
D4: Alpha Subsea Systems | G4: Beta Energy Equipment (peer)
B5: Metric | D5: FY2022 | E5: FY2023 | F5: FY2024 | G5: FY2022 | H5: FY2023 | I5: FY2024
B6: Revenue | D6: =Inputs!D6 -> 3200 | E6: =Inputs!E6 -> 3650 | F6: =Inputs!F6 -> 4050 | G6: =Inputs!D14 -> 5400 | H6: =Inputs!E14 -> 6100 | I6: =Inputs!F14 -> 6700
B7: COGS | D7: =Inputs!D7 -> 2500 | E7: =Inputs!E7 -> 2850 | F7: =Inputs!F7 -> 3160 | G7: =Inputs!D15 -> 4320 | H7: =Inputs!E15 -> 4880 | I7: =Inputs!F15 -> 5360
B8: Receivables | D8: =Inputs!D8 -> 720 | E8: =Inputs!E8 -> 880 | F8: =Inputs!F8 -> 1010 | G8: =Inputs!D16 -> 760 | H8: =Inputs!E16 -> 850 | I8: =Inputs!F16 -> 930
B9: Inventory | D9: =Inputs!D9 -> 780 | E9: =Inputs!E9 -> 900 | F9: =Inputs!F9 -> 1010 | G9: =Inputs!D17 -> 720 | H9: =Inputs!E17 -> 800 | I9: =Inputs!F17 -> 870
B10: Payables | D10: =Inputs!D10 -> 420 | E10: =Inputs!E10 -> 470 | F10: =Inputs!F10 -> 520 | G10: =Inputs!D18 -> 900 | H10: =Inputs!E18 -> 1020 | I10: =Inputs!F18 -> 1120
B12: CASH CONVERSION CYCLE
B13: DSO (Receivables days) | D13: =D8/D6*365 -> 82.125 | E13: =E8/E6*365 -> 88 | F13: =F8/F6*365 -> 91.024691 | G13: =G8/G6*365 -> 51.37037 | H13: =H8/H6*365 -> 50.860656 | I13: =I8/I6*365 -> 50.664179
B14: DIO (Inventory days) | D14: =D9/D7*365 -> 113.88 | E14: =E9/E7*365 -> 115.26316 | F14: =F9/F7*365 -> 116.66139 | G14: =G9/G7*365 -> 60.833333 | H14: =H9/H7*365 -> 59.836066 | I14: =I9/I7*365 -> 59.244403
B15: DPO (Payables days) | D15: =D10/D7*365 -> 61.32 | E15: =E10/E7*365 -> 60.192982 | F15: =F10/F7*365 -> 60.063291 | G15: =G10/G7*365 -> 76.041667 | H15: =H10/H7*365 -> 76.290984 | I15: =I10/I7*365 -> 76.268657
B16: CCC = DSO + DIO - DPO | D16: =D13+D14-D15 -> 134.685 | E16: =E13+E14-E15 -> 143.07018 | F16: =F13+F14-F15 -> 147.62279 | G16: =G13+G14-G15 -> 36.162037 | H16: =H13+H14-H15 -> 34.405738 | I16: =I13+I14-I15 -> 33.639925
B18: NET WORKING CAPITAL
B19: NWC (AR + Inv - AP) | D19: =D8+D9-D10 -> 1080 | E19: =E8+E9-E10 -> 1310 | F19: =F8+F9-F10 -> 1500 | G19: =G8+G9-G10 -> 580 | H19: =H8+H9-H10 -> 630 | I19: =I8+I9-I10 -> 680
B20: NWC as % of revenue | D20: =D19/D6 -> 0.3375 | E20: =E19/E6 -> 0.35890411 | F20: =F19/F6 -> 0.37037037 | G20: =G19/G6 -> 0.10740741 | H20: =H19/H6 -> 0.10327869 | I20: =I19/I6 -> 0.10149254
B22: READ-OUT (FY2023): Alpha ties up far more cash than Beta: a much longer cash conversion cycle and a higher share of revenue locked on the balance sheet.

Sheet Levers
B1: CASH-RELEASE LEVERS — Alpha Systems (FY2023 basis)
B2: Cash released = (current days - target days) / 365 x annual driver. Editable targets in blue.
B4: LEVER 1 — Reduce inventory days (DIO)
B5: Alpha current DIO | D5: ='WC Analysis'!E14 -> 115.26316 | G5: From WC Analysis, FY2023.
B6: Target DIO (editable) | D6: 90
B7: Days improvement | D7: =MAX(0,'WC Analysis'!E14-D6) -> 25.263158
B8: Annual COGS ($mm) | D8: =Inputs!E7 -> 2850
B9: CASH RELEASED ($mm) | D9: =D7/365*Inputs!E7 -> 197.26027 | G9: One-off cash freed from the balance sheet.
B10: Trade-off | D10: Leaner stock raises stockout / lead-time risk on long-cycle equipment
B12: LEVER 2 — Extend payables days (DPO) toward peer
B13: Alpha current DPO | D13: ='WC Analysis'!E15 -> 60.192982 | G13: From WC Analysis, FY2023.
B14: Target DPO (editable) | D14: 72
B15: Days improvement | D15: =MAX(0,D14-'WC Analysis'!E15) -> 11.807018
B16: Annual COGS ($mm) | D16: =Inputs!E7 -> 2850
B17: CASH RELEASED ($mm) | D17: =D15/365*Inputs!E7 -> 92.191781 | G17: One-off cash freed by paying suppliers over a longer cycle.
B18: Trade-off | D18: Pushing terms can strain suppliers or cost early-payment discounts
B20: LEVER 3 — Reduce receivables days (DSO) toward peer
B21: Alpha current DSO | D21: ='WC Analysis'!E13 -> 88 | G21: From WC Analysis, FY2023.
B22: Target DSO (editable) | D22: 70
B23: Days improvement | D23: =MAX(0,'WC Analysis'!E13-D22) -> 18
B24: Annual Revenue ($mm) | D24: =Inputs!E6 -> 3650
B25: CASH RELEASED ($mm) | D25: =D23/365*Inputs!E6 -> 180 | G25: One-off cash freed by collecting from customers sooner.
B26: Trade-off | D26: Faster collection is a business-partnering effort (terms, milestone billing, credit control) with commercial teams; pushing too hard could strain key customer relationships or require early-payment discounts.
B28: TOTAL POTENTIAL CASH RELEASED ($mm) | D28: =D9+D17+D25 -> 469.45205
B29: as % of FY2023 revenue | D29: =(D9+D17+D25)/Inputs!E6 -> 0.128617
